setup.py
common/__init__.py
common/decorators.py
common/descriptors.py
common/errors.py
common/metaclasses.py
common/utils.py
common/variables.py
gui/__init__.py
gui/add_contact.py
gui/client_gui.py
gui/del_contact.py
gui/main_window.py
gui/start_dialog.py
main/__init__.py
main/database.py
main/transport.py
project_logs/__init__.py
project_logs/config/__init__.py
project_logs/config/config_client_log.py
project_logs/config/config_server_log.py
tests/__init__.py
tests/test_client.py
tests/test_server.py
tests/test_utils.py
vyatkin_chat_client.egg-info/PKG-INFO
vyatkin_chat_client.egg-info/SOURCES.txt
vyatkin_chat_client.egg-info/dependency_links.txt
vyatkin_chat_client.egg-info/requires.txt
vyatkin_chat_client.egg-info/top_level.txt